boundaryscheme/__init__.py
boundaryscheme/boundaries.py
boundaryscheme/complex_winding_number.py
boundaryscheme/pyplot.py
boundaryscheme/schemes.py
boundaryscheme/utils.py
examples/__init__.py
examples/draw_detKLcurve.py
examples/draw_nbrzerosdetKL.py
examples/draw_symbol.py
tests/__init__.py
tests/test_import.py
boundaryscheme-2.4.dist-info/LICENSE
boundaryscheme-2.4.dist-info/METADATA
boundaryscheme-2.4.dist-info/WHEEL
boundaryscheme-2.4.dist-info/top_level.txt
boundaryscheme-2.4.dist-info/RECORD
