Metadata-Version: 2.1
Name: boundaryscheme
Version: 2.4
Summary: This library implements Kreiss-Lopatinskii determinant for numerical scheme with boundary
Home-page: UNKNOWN
Author: Pierre Le Barbenchon
License: UNKNOWN
Platform: UNKNOWN
Requires-Dist: sympy
Requires-Dist: scipy
Requires-Dist: numpy
Requires-Dist: matplotlib
